practice_poetry_project_release/__init__.py
practice_poetry_project_release/main.py
practice_poetry_project_release-0.2.2.dist-info/METADATA
practice_poetry_project_release-0.2.2.dist-info/WHEEL
practice_poetry_project_release-0.2.2.dist-info/RECORD
