Metadata-Version: 2.1
Name: practice-poetry-project-release
Version: 0.2.2
Summary: 
Author: nakayamaryo0731
Author-email: ryo_nakayama@caddi.jp
Requires-Python: >=3.12,<4.0
Classifier: Programming Language :: Python :: 3
Classifier: Programming Language :: Python :: 3.12
Requires-Dist: flask (>=3.0.3,<4.0.0)
Requires-Dist: flask-cors (>=4.0.1,<5.0.0)
Requires-Dist: flask-sqlalchemy (>=3.1.1,<4.0.0)
